tagoio_sdk/__init__.py
tagoio_sdk/config.py
tagoio_sdk/params.py
tagoio_sdk/regions.py
tagoio_sdk/types.py
tagoio_sdk/common/Cache.py
tagoio_sdk/common/Common_Type.py
tagoio_sdk/common/Hash_Generator.py
tagoio_sdk/common/tagoio_module.py
tagoio_sdk/infrastructure/api_request.py
tagoio_sdk/infrastructure/api_socket.py
tagoio_sdk/infrastructure/api_sse.py
tagoio_sdk/modules/Account/Account_Types.py
tagoio_sdk/modules/Account/Billing_Type.py
tagoio_sdk/modules/Account/Buckets_Type.py
tagoio_sdk/modules/Account/Dashboards_Type.py
tagoio_sdk/modules/Account/Device_Type.py
tagoio_sdk/modules/Account/IntegrationNetworkType.py
tagoio_sdk/modules/Account/Notification_Type.py
tagoio_sdk/modules/Account/Profile_Type.py
tagoio_sdk/modules/Account/Run_Type.py
tagoio_sdk/modules/Analysis/Analysis.py
tagoio_sdk/modules/Analysis/Analysis_Type.py
tagoio_sdk/modules/Device/Device.py
tagoio_sdk/modules/Device/Device_Type.py
tagoio_sdk/modules/Resources/Access.py
tagoio_sdk/modules/Resources/Access_Types.py
tagoio_sdk/modules/Resources/Account.py
tagoio_sdk/modules/Resources/AccountDeprecated.py
tagoio_sdk/modules/Resources/Account_Types.py
tagoio_sdk/modules/Resources/Actions.py
tagoio_sdk/modules/Resources/Actions_Types.py
tagoio_sdk/modules/Resources/Analyses.py
tagoio_sdk/modules/Resources/Analysis_Types.py
tagoio_sdk/modules/Resources/Billing.py
tagoio_sdk/modules/Resources/Billing_Type.py
tagoio_sdk/modules/Resources/Buckets.py
tagoio_sdk/modules/Resources/Buckets_Type.py
tagoio_sdk/modules/Resources/Dashboards.py
tagoio_sdk/modules/Resources/Dashboards_Type.py
tagoio_sdk/modules/Resources/Device_Type.py
tagoio_sdk/modules/Resources/Devices.py
tagoio_sdk/modules/Resources/Dictionaries.py
tagoio_sdk/modules/Resources/Dictionaries_Types.py
tagoio_sdk/modules/Resources/Files.py
tagoio_sdk/modules/Resources/Files_Types.py
tagoio_sdk/modules/Resources/Integration.py
tagoio_sdk/modules/Resources/IntegrationConnector.py
tagoio_sdk/modules/Resources/IntegrationConnectorType.py
tagoio_sdk-5.0.4.dist-info/METADATA
tagoio_sdk-5.0.4.dist-info/WHEEL
tagoio_sdk-5.0.4.dist-info/licenses/LICENSE
tagoio_sdk-5.0.4.dist-info/RECORD
