Metadata-Version: 2.4
Name: tagoio-sdk
Version: 5.0.4
Summary: Official Python SDK for TagoIO
Project-URL: Homepage, https://tago.io/
Project-URL: Repository, https://github.com/tago-io/sdk-python/
Project-URL: Documentation, https://py.sdk.tago.io/
Project-URL: Changelog, https://github.com/tago-io/sdk-python/releases
Project-URL: Bug Tracker, https://github.com/tago-io/sdk-python/issues
Author-email: "TagoIO Inc." <contact@tago.io>
License: Apache-2.0
License-File: LICENSE
Keywords: analysis,device,iot,sensor,tago,tagoio
Classifier: Development Status :: 5 - Production/Stable
Classifier: Intended Audience :: Developers
Classifier: License :: OSI Approved :: Apache Software License
Classifier: Programming Language :: Python :: 3 :: Only
Classifier: Programming Language :: Python :: 3.11
Classifier: Programming Language :: Python :: 3.12
Classifier: Programming Language :: Python :: 3.13
Classifier: Topic :: Internet :: WWW/HTTP
Classifier: Topic :: Software Development :: Libraries :: Python Modules
Requires-Python: >=3.11
Requires-Dist: python-dateutil>=2.9.0
Requires-Dist: requests-toolbelt>=1.0.0
Requires-Dist: requests<3.0.0,>=2.32.0
Requires-Dist: sseclient-py>=1.8.0
Provides-Extra: dev
Requires-Dist: pytest>=8.4.1; extra == 'dev'
Requires-Dist: requests-mock>=1.12.1; extra == 'dev'
Requires-Dist: ruff>=0.12.7; extra == 'dev'
Requires-Dist: sphinx>=8.2.3; extra == 'dev'
